[{
  "caption": "Figure 4: Commits per author vs average rationale density",
  "captionBoundary": {
    "x1": 320.385986328125,
    "x2": 555.7614135742188,
    "y1": 504.1633605957031,
    "y2": 509.79400634765625
  },
  "figType": "Figure",
  "imageText": ["Number", "of", "authors", "1", "2", "3", "5", "6", "14", "Number", "of", "commits", "=", "16", "Rationale", "density", "=", "0.2", "Rationale", "density", "=", "0.7", "sit", "y", "D", "en", "na", "le", "Ra", "tio", "ag", "e", "Av", "er", "1.0", "0.8", "0.6", "0.4", "0.2", "0.0", "0", "20", "40", "60", "80", "Number", "of", "commits", "per", "author"],
  "name": "4",
  "page": 5,
  "regionBoundary": {
    "x1": 359.03999999999996,
    "x2": 517.4399999999999,
    "y1": 304.8,
    "y2": 485.28
  },
  "renderDpi": 150,
  "renderURL": "../datacollection/pdf_analysis/iwpc-icpc2024/figures/10_1145-3643916_3644413-Figure4-1.png"
}, {
  "caption": "Figure 2: Most frequent words per category, without overlap",
  "captionBoundary": {
    "x1": 68.68299865722656,
    "x2": 279.15081787109375,
    "y1": 571.329345703125,
    "y2": 587.9190063476562
  },
  "figType": "Figure",
  "imageText": ["’check’", "21,", "’reaper’", "20", "(c)", "Supporting", "Facts", "word", "cloud.", "Most", "frequent", "words:", "’kill’", "46,", "’will’", "29,", "’tasks’", "28,", "’node’", "27,", "’killed’", "26,", "’current’", "26,", "’allocation’", "24,", "’set’", "23,", "(b)", "Rationale", "word", "cloud.", "Most", "frequent", "words:", "’might’:", "5,", "’make’", "5,", "’will’", "4,", "’Fixes’", "4,", "’help’", "4,", "’debugging’", "4,", "’later’", "4,", "’use’", "3,", "’reduce’", "3,", "’useful’", "3", "’check’", "16", "(a)", "Decision", "word", "cloud.", "Most", "frequent", "words:", "’add’", "28,", "’use’", "28,", "’remove’", "28,", "’kill’", "27,", "’tasks’", "22,", "’set’", "20,", "’cpuset’", "20,", "’instead’", "19,", "’introduce’", "18,"],
  "name": "2",
  "page": 5,
  "regionBoundary": {
    "x1": 96.96,
    "x2": 250.07999999999998,
    "y1": 92.64,
    "y2": 556.3199999999999
  },
  "renderDpi": 150,
  "renderURL": "../datacollection/pdf_analysis/iwpc-icpc2024/figures/10_1145-3643916_3644413-Figure2-1.png"
}, {
  "caption": "Figure 3: Commit message size versus rationale density",
  "captionBoundary": {
    "x1": 326.2770080566406,
    "x2": 549.8711547851562,
    "y1": 287.1213684082031,
    "y2": 292.75201416015625
  },
  "figType": "Figure",
  "imageText": ["Number", "of", "commits", "3", "6", "9", "12", "15", "18", "21", "24", "27", "30", "33", "36", "sit", "y", "D", "en", "na", "le", "Ra", "tio", "1.0", "0.8", "0.6", "0.4", "0.2", "0.0", "0", "5", "10", "15", "20", "25", "30", "35", "40", "Commit", "message", "size", "(Number", "of", "sentences)"],
  "name": "3",
  "page": 5,
  "regionBoundary": {
    "x1": 359.03999999999996,
    "x2": 519.84,
    "y1": 87.84,
    "y2": 268.32
  },
  "renderDpi": 150,
  "renderURL": "../datacollection/pdf_analysis/iwpc-icpc2024/figures/10_1145-3643916_3644413-Figure3-1.png"
}, {
  "caption": "Table 1: Labelling codebook",
  "captionBoundary": {
    "x1": 381.6400146484375,
    "x2": 494.21697998046875,
    "y1": 85.72634887695312,
    "y2": 91.35699462890625
  },
  "figType": "Table",
  "imageText": ["(i.e.,", "does", "not", "contain", "English", "sentences)", "Decision", "An", "action", "or", "a", "change", "that", "has", "been", "made,", "includ-", "ing", "a", "description", "of", "the", "patch", "behaviour", "Rationale", "Reason", "for", "a", "decision", "or", "value", "judgment", "Supporting", "Facts", "A", "narration", "of", "facts", "used", "to", "support", "a", "decision", "Inapplicable", "Pre-processing", "error", "or", "bad", "sentences", "Label", "Meaning"],
  "name": "1",
  "page": 1,
  "regionBoundary": {
    "x1": 316.8,
    "x2": 557.28,
    "y1": 105.6,
    "y2": 187.2
  },
  "renderDpi": 150,
  "renderURL": "../datacollection/pdf_analysis/iwpc-icpc2024/figures/10_1145-3643916_3644413-Table1-1.png"
}, {
  "caption": "Figure 5: Monthly evolution of the average rationale density",
  "captionBoundary": {
    "x1": 183.99000549316406,
    "x2": 427.99957275390625,
    "y1": 210.64938354492188,
    "y2": 216.280029296875
  },
  "figType": "Figure",
  "imageText": ["Average", "rationale", "density", "sit", "y", "D", "en", "na", "le", "Ra", "tio", "ag", "e", "Av", "er", "1.0", "0.8", "0.6", "0.4", "0.2", "0.0", "Time", "(months)", "2004-07", "2005-01", "2005-07", "2006-01", "2006-07", "2007-01", "2007-07", "2008-01", "2008-07", "2009-01", "2009-07", "2010-01", "2010-07", "2011-01", "2011-07", "2012-01", "2012-07", "2013-01", "2013-07", "2014-01", "2014-07", "2015-01", "2015-07", "2016-01", "2016-07", "2017-01", "2017-07", "2018-01", "2018-07", "2019-01", "2019-07", "2020-01", "2020-07", "2021-01", "2021-07", "2022-01", "2022-07", "2023-01"],
  "name": "5",
  "page": 6,
  "regionBoundary": {
    "x1": 132.96,
    "x2": 480.47999999999996,
    "y1": 86.88,
    "y2": 192.48
  },
  "renderDpi": 150,
  "renderURL": "../datacollection/pdf_analysis/iwpc-icpc2024/figures/10_1145-3643916_3644413-Figure5-1.png"
}, {
  "caption": "Figure 6: Yearly evolution of the average rationale density, the average commit message size and the number of commits",
  "captionBoundary": {
    "x1": 62.505001068115234,
    "x2": 549.4752197265625,
    "y1": 358.08636474609375,
    "y2": 363.7170104980469
  },
  "figType": "Figure",
  "imageText": ["Average", "rationale", "density", "Average", "commit", "message", "size", "Number", "of", "commits", "m", "its", "f", "c", "om", "be", "r", "o", "Nu", "m", "40", "30", "20", "10", "si", "ze", "sa", "ge", "m", "es", "m", "it", "Co", "m", "8", "7", "6", "5", "4", "sit", "y", "D", "en", "na", "le", "Ra", "tio", "ag", "e", "Av", "er", "0.70", "0.65", "0.60", "0.55", "2006", "2008", "2010", "2012", "2014", "2016", "2018", "2020", "2022", "Time", "(years)"],
  "name": "6",
  "page": 6,
  "regionBoundary": {
    "x1": 132.96,
    "x2": 478.08,
    "y1": 234.72,
    "y2": 339.84
  },
  "renderDpi": 150,
  "renderURL": "../datacollection/pdf_analysis/iwpc-icpc2024/figures/10_1145-3643916_3644413-Figure6-1.png"
}, {
  "caption": "Table 2: An example commit with labelled sentences from our dataset",
  "captionBoundary": {
    "x1": 164.59600830078125,
    "x2": 447.0966491699219,
    "y1": 85.72634887695312,
    "y2": 91.35699462890625
  },
  "figType": "Table",
  "imageText": ["Sentence", "Labelling", "mm,", "oom:", "introduce", "independent", "oom", "killer", "ratelimit", "state", "Decision", "printk_ratelimit()", "uses", "the", "global", "ratelimit", "state", "for", "all", "printks", "Supporting", "Facts", "The", "oom", "killer", "should", "not", "be", "subjected", "to", "this", "state", "just", "because", "another", "subsystem", "or", "driver", "may", "be", "flooding", "the", "kernel", "log", "Rationale", "This", "patch", "introduces", "printk", "ratelimiting", "specifically", "for", "the", "oom", "killer.", "Decision"],
  "name": "2",
  "page": 2,
  "regionBoundary": {
    "x1": 68.64,
    "x2": 541.4399999999999,
    "y1": 105.6,
    "y2": 157.44
  },
  "renderDpi": 150,
  "renderURL": "../datacollection/pdf_analysis/iwpc-icpc2024/figures/10_1145-3643916_3644413-Table2-1.png"
}, {
  "caption": "Figure 8: Evolution of average rationale density, average commit message size, and number of commits for top 5 contributors",
  "captionBoundary": {
    "x1": 53.79800033569336,
    "x2": 558.1802978515625,
    "y1": 340.6363525390625,
    "y2": 346.2669982910156
  },
  "figType": "Figure",
  "imageText": ["Average", "rationale", "density", "Average", "commit", "message", "size", "Number", "of", "commits", "0", "5", "10", "15", "20", "25", "30", "35", "Nu", "m", "be", "r", "o", "f", "c", "om", "m", "its", "si", "ze", "sa", "ge", "m", "es", "m", "it", "Co", "m", "16", "14", "12", "10", "8", "6", "4", "sit", "y", "D", "en", "na", "le", "Ra", "tio", "ag", "e", "Av", "er", "0.8", "0.7", "0.6", "0.5", "0.4", "2006", "2008", "2010", "2012", "2014", "2016", "2018", "2020", "2022", "Time", "(years)"],
  "name": "8",
  "page": 7,
  "regionBoundary": {
    "x1": 132.96,
    "x2": 477.59999999999997,
    "y1": 216.0,
    "y2": 322.56
  },
  "renderDpi": 150,
  "renderURL": "../datacollection/pdf_analysis/iwpc-icpc2024/figures/10_1145-3643916_3644413-Figure8-1.png"
}, {
  "caption": "Figure 7: Yearly evolution of the average rationale density, the average decision density and the average supporting facts",
  "captionBoundary": {
    "x1": 62.4379997253418,
    "x2": 549.5426635742188,
    "y1": 199.31033325195312,
    "y2": 204.94097900390625
  },
  "figType": "Figure",
  "imageText": ["De", "ns", "ity", "Average", "decision", "density", "Average", "rationale", "density", "Average", "supporting", "facts", "density", "ag", "e", "Av", "er", "0.8", "0.7", "0.6", "0.5", "0.4", "0.3", "0.2", "0.1", "2006", "2008", "2010", "2012", "2014", "2016", "2018", "2020", "2022", "Time", "(years)"],
  "name": "7",
  "page": 7,
  "regionBoundary": {
    "x1": 134.4,
    "x2": 479.52,
    "y1": 86.88,
    "y2": 181.44
  },
  "renderDpi": 150,
  "renderURL": "../datacollection/pdf_analysis/iwpc-icpc2024/figures/10_1145-3643916_3644413-Figure7-1.png"
}, {
  "caption": "Figure 1: Distribution of the sentences in our OOM dataset",
  "captionBoundary": {
    "x1": 319.9599914550781,
    "x2": 556.1871337890625,
    "y1": 187.21237182617188,
    "y2": 192.843017578125
  },
  "figType": "Figure",
  "imageText": ["Decision", "556136", "220", "427", "431", "397"],
  "name": "1",
  "page": 3,
  "regionBoundary": {
    "x1": 386.88,
    "x2": 489.12,
    "y1": 82.56,
    "y2": 174.23999999999998
  },
  "renderDpi": 150,
  "renderURL": "../datacollection/pdf_analysis/iwpc-icpc2024/figures/10_1145-3643916_3644413-Figure1-1.png"
}, {
  "caption": "Table 3: Inter-rater reliability table",
  "captionBoundary": {
    "x1": 103.07797241210938,
    "x2": 244.46279907226562,
    "y1": 85.72634887695312,
    "y2": 91.35699462890625
  },
  "figType": "Table",
  "imageText": ["1", "20", "0.596", "0.514", "0.489", "2", "20", "0.733", "0.487", "0.596", "3", "20", "1.0", "0.933", "1.0", "4", "40", "0.899", "0.929", "1.0", "5", "20", "0.928", "0.796", "0.738", "6", "20", "0.861", "0.80", "0.40", "7", "20", "1.0", "0.853", "0.863", "8", "20", "0.865", "0.498", "0.666", "9", "20", "0.644", "0.261", "0.799", "10", "20", "0.286", "0.20", "0.280", "11", "20", "0.796", "0.865", "0.598", "12", "20", "0.777", "0.707", "0.665", "13", "20", "0.925", "0.498", "0.850", "14", "20", "0.569", "0.343", "0.603", "15", "20", "1.0", "0.932", "0.731", "16", "20", "0.918", "0.555", "0.859", "17", "20", "0.822", "0.775", "0.733", "18", "6", "0.593", "0.326", "0.175", "All", "366", "0.748", "0.603", "0.648", "Batch", "Size", "Fleiss", "Kappa", "Decision", "Rationale", "Supporting", "Facts"],
  "name": "3",
  "page": 3,
  "regionBoundary": {
    "x1": 84.0,
    "x2": 262.08,
    "y1": 105.6,
    "y2": 276.0
  },
  "renderDpi": 150,
  "renderURL": "../datacollection/pdf_analysis/iwpc-icpc2024/figures/10_1145-3643916_3644413-Table3-1.png"
}, {
  "caption": "Table 6: Research questions and their answers.",
  "captionBoundary": {
    "x1": 211.60198974609375,
    "x2": 400.09417724609375,
    "y1": 573.29833984375,
    "y2": 578.9290161132812
  },
  "figType": "Table",
  "imageText": ["Structure", "of", "commit", "messages", "RQ7.", "In", "what", "order", "do", "the", "categories", "mostly", "appear?", "Decision", "then", "Supporting", "Facts", "then", "Rationale", "then", "Decision.", "The", "yearly", "evolution", "of", "rationale", "density", "is", "rather", "consistent", "around", "0.6", "for", "the", "five", "core", "contributors.", "This", "changes", "in", "the", "recent", "years", "2020,", "2021", "and", "2022", "(with", "1", "commit", "per", "year).", "RQ5.", "How", "does", "rationale", "evolve", "over", "time?", "The", "yearly", "evolution", "of", "rationale", "density", "is", "rather", "consistent", "around", "0.5", "and", "0.7.", "The", "monthly", "evolution", "of", "rationale", "density", "however", "shows", "great", "fluctuation.", "RQ6.", "How", "does", "rationale", "evolve", "over", "time", "for", "the", "five", "core", "contributors?", "Evolution", "of", "rationale", "over", "time", "RQ3.", "Does", "the", "quantity", "of", "rationale", "reported", "depend", "on", "the", "commit", "message", "size?", "The", "quantity", "of", "rationale", "reported", "does", "not", "depend", "on", "the", "commit", "message", "size", "(in", "terms", "of", "number", "of", "sentences).", "RQ4.", "Does", "the", "quantity", "of", "rationale", "reported", "depend", "on", "the", "developer", "experience?", "The", "quantity", "of", "rationale", "reported", "does", "not", "depend", "on", "the", "developer", "experience.", "Factors", "impacting", "rationale", "Topic", "Research", "question", "Answer", "Presence", "of", "rationale", "RQ1.", "How", "many", "commits", "contain", "rationale?", "98.9%", "of", "the", "commits", "contain", "rationale.", "RQ2.", "How", "much", "of", "the", "commit", "contains", "rationale?", "Around", "60%", "of", "the", "commit", "message", "contains", "rationale", "information."],
  "name": "6",
  "page": 8,
  "regionBoundary": {
    "x1": 60.96,
    "x2": 549.12,
    "y1": 593.76,
    "y2": 708.0
  },
  "renderDpi": 150,
  "renderURL": "../datacollection/pdf_analysis/iwpc-icpc2024/figures/10_1145-3643916_3644413-Table6-1.png"
}, {
  "caption": "Figure 9: Category distribution over the normalized positions of commit message sentences (considering overlap).",
  "captionBoundary": {
    "x1": 53.79800033569336,
    "x2": 295.6379089355469,
    "y1": 221.36135864257812,
    "y2": 237.95098876953125
  },
  "figType": "Figure",
  "imageText": ["Decision", "Rationale", "Supporting", "Facts", "m", "its", "f", "c", "om", "be", "r", "o", "Nu", "m", "100", "150", "200", "250", "300", "350", "0", "50", "0.0", "0.1", "0.2", "0.3", "0.4", "0.5", "0.6", "0.7", "0.8", "0.9", "1.0", "Normalized", "position", "of", "the", "sentence", "in", "the", "commit", "message"],
  "name": "9",
  "page": 8,
  "regionBoundary": {
    "x1": 76.8,
    "x2": 274.08,
    "y1": 86.88,
    "y2": 203.04
  },
  "renderDpi": 150,
  "renderURL": "../datacollection/pdf_analysis/iwpc-icpc2024/figures/10_1145-3643916_3644413-Figure9-1.png"
}, {
  "caption": "Table 4: Example of the dataset structure with one entry",
  "captionBoundary": {
    "x1": 191.97000122070312,
    "x2": 419.7242126464844,
    "y1": 85.72634887695312,
    "y2": 91.35699462890625
  },
  "figType": "Table",
  "imageText": ["commit", "number", "4", "commit", "ID", "C_kwDOACN7MtoAKGExOWNhZDA2OTE1OTdlYjc5YzEyM2I4YTE5YTlmYWJhNWFiN2Q5MGU", "author", "name", "Andrew", "Morton", "committer", "name", "akpm", "message", "mm/oom_kill.c:", "fix", "vm_oom_kill_table[]", "ifdeffery", "arm", "allnoconfig:", "mm/oom_kill.c:60:25:", "warning:", "’vm_oom_kill_table’", "defined", "but", "not", "used", "Column", "Value"],
  "name": "4",
  "page": 4,
  "regionBoundary": {
    "x1": 60.96,
    "x2": 551.04,
    "y1": 105.6,
    "y2": 161.28
  },
  "renderDpi": 150,
  "renderURL": "../datacollection/pdf_analysis/iwpc-icpc2024/figures/10_1145-3643916_3644413-Table4-1.png"
}, {
  "caption": "Table 5: An example commit with multi-labelled sentences from our dataset, using the same colour scheme as in Figure 1.",
  "captionBoundary": {
    "x1": 59.44300079345703,
    "x2": 552.2412109375,
    "y1": 234.24935913085938,
    "y2": 239.8800048828125
  },
  "figType": "Table",
  "imageText": ["URL", "https://api.github.com/repos/torvalds/linux/git/commits/a19cad0691597eb79c123b8a19a9faba5ab7d90e", "message_preprocessed", "mm/oom_kill.c:", "fix", "vm_oom_kill_table[]", "ifdeffery", "Decision", "yes", "Rationale", "yes", "Supporting", "Facts", "no", "[-Wunused-variable]", "60", "|", "static", "struct", "ctl_table", "vm_oom_kill_table[]", "=", "Cc:", "Luis", "Chamberlain", "<mcgrof@kernel.org>", "Signed-off-by:", "Andrew", "Morton", "<akpm@linux-foundation.org>"],
  "name": "5",
  "page": 4,
  "regionBoundary": {
    "x1": 60.96,
    "x2": 551.04,
    "y1": 162.72,
    "y2": 220.32
  },
  "renderDpi": 150,
  "renderURL": "../datacollection/pdf_analysis/iwpc-icpc2024/figures/10_1145-3643916_3644413-Table5-1.png"
}]