[{
  "caption": "Figure 1: Patient-robot interaction in the triage system [34]",
  "captionBoundary": {
    "x1": 53.979000091552734,
    "x2": 293.8553466796875,
    "y1": 223.57632446289062,
    "y2": 229.20697021484375
  },
  "figType": "Figure",
  "imageText": [],
  "name": "1",
  "page": 1,
  "regionBoundary": {
    "x1": 100.8,
    "x2": 246.23999999999998,
    "y1": 82.56,
    "y2": 210.23999999999998
  },
  "renderDpi": 150,
  "renderURL": "../datacollection/pdf_analysis/seams-seams2024/figures/10_1145-3643915_3644082-Figure1-1.png"
}, {
  "caption": "Figure 2: Vision of human empowerment with regards to systems.",
  "captionBoundary": {
    "x1": 317.9549865722656,
    "x2": 558.1923828125,
    "y1": 237.09432983398438,
    "y2": 253.68402099609375
  },
  "figType": "Figure",
  "imageText": ["Models", "Models", "Human", "SASTS", "Third", "Party", "Auditor", "Connector", "Mediator"],
  "name": "2",
  "page": 2,
  "regionBoundary": {
    "x1": 324.0,
    "x2": 551.04,
    "y1": 84.0,
    "y2": 221.28
  },
  "renderDpi": 150,
  "renderURL": "../datacollection/pdf_analysis/seams-seams2024/figures/10_1145-3643915_3644082-Figure2-1.png"
}, {
  "caption": "Figure 4: Illustration of the introduction of connectors and mediators in DAiSY.",
  "captionBoundary": {
    "x1": 317.9549865722656,
    "x2": 558.1893920898438,
    "y1": 352.6153564453125,
    "y2": 369.2049865722656
  },
  "figType": "Figure",
  "imageText": ["Robot", "Logic", "Triage", "Back-end", "Robot", "Triage", "System", "Clinician", "Model", "Clinician", "Connector", "Patient", "Clinician", "Patient", "Models", "Clinician", "Models", "Patient", "Model", "Triage", "Mediator", "Patient", "Connector"],
  "name": "4",
  "page": 3,
  "regionBoundary": {
    "x1": 324.0,
    "x2": 551.52,
    "y1": 202.56,
    "y2": 337.44
  },
  "renderDpi": 150,
  "renderURL": "../datacollection/pdf_analysis/seams-seams2024/figures/10_1145-3643915_3644082-Figure4-1.png"
}]